agentic/__init__.py
agentic/agentic.py
agentic/state.py
agentic/backend/__init__.py
agentic/backend/agent.py
agentic/components/__init__.py
agentic/components/chat.py
agentic/components/loading_icon.py
agentic/components/modal.py
agentic/components/navbar.py
agentify-0.1.0.dist-info/LICENSE
agentify-0.1.0.dist-info/METADATA
agentify-0.1.0.dist-info/WHEEL
agentify-0.1.0.dist-info/top_level.txt
agentify-0.1.0.dist-info/RECORD
