Metadata-Version: 2.1
Name: agentify
Version: 0.1.0
Summary: A Python package for agent-based frameworks
Home-page: https://github.com/yourusername/agentflow
Author: Your Name
Author-email: your.email@example.com
Classifier: Development Status :: 3 - Alpha
Classifier: Intended Audience :: Developers
Classifier: Programming Language :: Python :: 3
Classifier: Programming Language :: Python :: 3.11
Classifier: License :: OSI Approved :: MIT License
Classifier: Operating System :: OS Independent
Requires-Python: >=3.11
License-File: LICENSE
